tempres/__init__.py
tempres/__main__.py
tempres/const.py
tempres/main.py
tempres/maindb.py
tempres/mainplt.py
tempres/mainpub.py
tempres/timedpath.py
tempres-0.0.2.dist-info/LICENSE.md
tempres-0.0.2.dist-info/METADATA
tempres-0.0.2.dist-info/WHEEL
tempres-0.0.2.dist-info/entry_points.txt
tempres-0.0.2.dist-info/top_level.txt
tempres-0.0.2.dist-info/RECORD
