Metadata-Version: 2.1
Name: tempres
Version: 0.0.2
Summary: collect temperature and pressure data from a mpy-modcore device
Home-page: https://github.com/kr-g/tempres
Author: k. goger
Author-email: k.r.goger+tempres@gmail.com
License: other / AGPLv3+
Keywords: micropython esp32 esp8266 modcore home-automation
Platform: UNKNOWN
Classifier: Development Status :: 3 - Alpha
Classifier: Operating System :: POSIX :: Linux
Classifier: Operating System :: OS Independent
Classifier: Environment :: Console
Classifier: Intended Audience :: Developers
Classifier: Intended Audience :: Information Technology
Classifier: Topic :: Software Development :: Embedded Systems
Classifier: Topic :: Utilities
Classifier: Topic :: Home Automation
Classifier: Topic :: Software Development :: Libraries :: Python Modules
Classifier: Programming Language :: Python :: Implementation :: MicroPython
Classifier: Programming Language :: Python :: 3
Classifier: License :: Free For Home Use
Classifier: License :: Free for non-commercial use
Classifier: License :: Free To Use But Restricted
Classifier: License :: Other/Proprietary License
Classifier: License :: OSI Approved :: GNU Affero General Public License v3 or later (AGPLv3+)
Requires-Python: >=3.10
License-File: LICENSE.md
Requires-Dist: SQLAlchemy
Requires-Dist: matplotlib
Requires-Dist: numpy
Requires-Dist: pyjsoncfg (==0.0.6)
